{
  "date": "2026-04-09",
  "model": "nba_props_v1",
  "projections": [
    {
      "player": "Scottie Barnes",
      "stat": "assists",
      "matchup": "Miami Heat @ Toronto Raptors",
      "line": 6.5,
      "base_proj": 8.7,
      "ha_adj": 0.14,
      "def_adj": -0.0,
      "b2b_adj": 0.0,
      "bias_adj": 0.0,
      "projection": 8.83,
      "std_dev": 3.1,
      "ci_low": 5.7,
      "ci_high": 11.9,
      "season_avg": 5.91,
      "rolling_avg": 9.16,
      "games_used": 10,
      "avg_minutes": 29.8,
      "low_minutes": false,
      "direction": "over",
      "raw_edge": 2.33,
      "edge_pct": 35.8,
      "prob_edge": 25.2,
      "model_prob": 77.4,
      "implied_prob": 52.2,
      "price": -109.0,
      "b2b": false,
      "over_price": -109.0,
      "under_price": -121.7
    },
    {
      "player": "Andrew Wiggins",
      "stat": "assists",
      "matchup": "Miami Heat @ Toronto Raptors",
      "line": 2.5,
      "base_proj": 1.97,
      "ha_adj": -0.2,
      "def_adj": -0.0,
      "b2b_adj": 0.0,
      "bias_adj": 0.0,
      "projection": 1.77,
      "std_dev": 1.58,
      "ci_low": 0.2,
      "ci_high": 3.3,
      "season_avg": 2.66,
      "rolling_avg": 1.86,
      "games_used": 10,
      "avg_minutes": 28.8,
      "low_minutes": false,
      "direction": "under",
      "raw_edge": -0.73,
      "edge_pct": -29.2,
      "prob_edge": 8.4,
      "model_prob": 67.8,
      "implied_prob": 59.4,
      "price": -146.5,
      "b2b": false,
      "over_price": 111.0,
      "under_price": -146.5
    },
    {
      "player": "Tyler Herro",
      "stat": "points",
      "matchup": "Miami Heat @ Toronto Raptors",
      "line": 21.5,
      "base_proj": 20.55,
      "ha_adj": -0.3,
      "def_adj": -0.07,
      "b2b_adj": 0.0,
      "bias_adj": 0.4,
      "projection": 20.58,
      "std_dev": 6.1,
      "ci_low": 14.5,
      "ci_high": 26.7,
      "season_avg": 21.19,
      "rolling_avg": 20.45,
      "games_used": 10,
      "avg_minutes": 34.4,
      "low_minutes": false,
      "direction": "under",
      "raw_edge": -0.92,
      "edge_pct": -4.3,
      "prob_edge": 1.0,
      "model_prob": 56.0,
      "implied_prob": 55.0,
      "price": -122.0,
      "b2b": false,
      "over_price": -107.3,
      "under_price": -122.0
    },
    {
      "player": "Brandon Ingram",
      "stat": "points",
      "matchup": "Miami Heat @ Toronto Raptors",
      "line": 21.2,
      "base_proj": 18.64,
      "ha_adj": 1.33,
      "def_adj": -0.03,
      "b2b_adj": 0.0,
      "bias_adj": 0.4,
      "projection": 20.34,
      "std_dev": 6.89,
      "ci_low": 13.5,
      "ci_high": 27.2,
      "season_avg": 21.3,
      "rolling_avg": 18.21,
      "games_used": 10,
      "avg_minutes": 31.2,
      "low_minutes": false,
      "direction": "under",
      "raw_edge": -0.86,
      "edge_pct": -4.1,
      "prob_edge": 1.0,
      "model_prob": 55.0,
      "implied_prob": 54.0,
      "price": -117.3,
      "b2b": false,
      "over_price": -111.0,
      "under_price": -117.3
    },
    {
      "player": "Bam Adebayo",
      "stat": "points",
      "matchup": "Miami Heat @ Toronto Raptors",
      "line": 20.8,
      "base_proj": 18.62,
      "ha_adj": -1.36,
      "def_adj": -0.07,
      "b2b_adj": 0.0,
      "bias_adj": 0.4,
      "projection": 17.59,
      "std_dev": 7.59,
      "ci_low": 10.0,
      "ci_high": 25.2,
      "season_avg": 19.99,
      "rolling_avg": 18.39,
      "games_used": 10,
      "avg_minutes": 34.5,
      "low_minutes": false,
      "direction": "under",
      "raw_edge": -3.21,
      "edge_pct": -15.4,
      "prob_edge": 13.5,
      "model_prob": 66.4,
      "implied_prob": 52.9,
      "price": -112.3,
      "b2b": false,
      "over_price": -116.0,
      "under_price": -112.3
    },
    {
      "player": "R.J. Barrett",
      "stat": "points",
      "matchup": "Miami Heat @ Toronto Raptors",
      "line": 20.5,
      "base_proj": 19.33,
      "ha_adj": 0.28,
      "def_adj": -0.03,
      "b2b_adj": 0.0,
      "bias_adj": 0.4,
      "projection": 19.98,
      "std_dev": 5.1,
      "ci_low": 14.9,
      "ci_high": 25.1,
      "season_avg": 19.09,
      "rolling_avg": 19.37,
      "games_used": 10,
      "avg_minutes": 30.8,
      "low_minutes": false,
      "direction": "under",
      "raw_edge": -0.52,
      "edge_pct": -2.5,
      "prob_edge": 0.7,
      "model_prob": 54.1,
      "implied_prob": 53.3,
      "price": -114.3,
      "b2b": false,
      "over_price": -114.0,
      "under_price": -114.3
    },
    {
      "player": "Scottie Barnes",
      "stat": "points",
      "matchup": "Miami Heat @ Toronto Raptors",
      "line": 17.8,
      "base_proj": 15.87,
      "ha_adj": 0.64,
      "def_adj": -0.03,
      "b2b_adj": 0.0,
      "bias_adj": 0.4,
      "projection": 16.89,
      "std_dev": 6.64,
      "ci_low": 10.2,
      "ci_high": 23.5,
      "season_avg": 18.21,
      "rolling_avg": 15.49,
      "games_used": 10,
      "avg_minutes": 29.8,
      "low_minutes": false,
      "direction": "under",
      "raw_edge": -0.91,
      "edge_pct": -5.1,
      "prob_edge": 1.7,
      "model_prob": 55.5,
      "implied_prob": 53.8,
      "price": -116.3,
      "b2b": false,
      "over_price": -112.7,
      "under_price": -116.3
    },
    {
      "player": "Norman Powell",
      "stat": "points",
      "matchup": "Miami Heat @ Toronto Raptors",
      "line": 17.5,
      "base_proj": 18.14,
      "ha_adj": -1.11,
      "def_adj": -0.06,
      "b2b_adj": 0.0,
      "bias_adj": 0.4,
      "projection": 17.37,
      "std_dev": 6.18,
      "ci_low": 11.2,
      "ci_high": 23.6,
      "season_avg": 21.95,
      "rolling_avg": 17.53,
      "games_used": 10,
      "avg_minutes": 27.6,
      "low_minutes": false,
      "direction": "under",
      "raw_edge": -0.13,
      "edge_pct": -0.7,
      "prob_edge": -1.7,
      "model_prob": 50.8,
      "implied_prob": 52.5,
      "price": -110.5,
      "b2b": false,
      "over_price": -117.5,
      "under_price": -110.5
    },
    {
      "player": "Andrew Wiggins",
      "stat": "points",
      "matchup": "Miami Heat @ Toronto Raptors",
      "line": 14.5,
      "base_proj": 15.43,
      "ha_adj": -0.24,
      "def_adj": -0.05,
      "b2b_adj": 0.0,
      "bias_adj": 0.4,
      "projection": 15.54,
      "std_dev": 4.7,
      "ci_low": 10.8,
      "ci_high": 20.2,
      "season_avg": 15.77,
      "rolling_avg": 15.38,
      "games_used": 10,
      "avg_minutes": 28.8,
      "low_minutes": false,
      "direction": "over",
      "raw_edge": 1.04,
      "edge_pct": 7.2,
      "prob_edge": 7.1,
      "model_prob": 58.8,
      "implied_prob": 51.7,
      "price": -107.0,
      "b2b": false,
      "over_price": -107.0,
      "under_price": -122.0
    },
    {
      "player": "Immanuel Quickley",
      "stat": "points",
      "matchup": "Miami Heat @ Toronto Raptors",
      "line": 13.5,
      "base_proj": 12.41,
      "ha_adj": -1.12,
      "def_adj": -0.02,
      "b2b_adj": 0.0,
      "bias_adj": 0.4,
      "projection": 11.67,
      "std_dev": 6.0,
      "ci_low": 5.7,
      "ci_high": 17.7,
      "season_avg": 16.69,
      "rolling_avg": 11.71,
      "games_used": 10,
      "avg_minutes": 29.2,
      "low_minutes": false,
      "direction": "under",
      "raw_edge": -1.83,
      "edge_pct": -13.6,
      "prob_edge": 7.0,
      "model_prob": 62.0,
      "implied_prob": 55.0,
      "price": -122.3,
      "b2b": false,
      "over_price": -107.3,
      "under_price": -122.3
    },
    {
      "player": "Jakob Poeltl",
      "stat": "points",
      "matchup": "Miami Heat @ Toronto Raptors",
      "line": 11.2,
      "base_proj": 13.1,
      "ha_adj": 0.05,
      "def_adj": -0.02,
      "b2b_adj": 0.0,
      "bias_adj": 0.4,
      "projection": 13.53,
      "std_dev": 6.11,
      "ci_low": 7.4,
      "ci_high": 19.6,
      "season_avg": 10.98,
      "rolling_avg": 13.45,
      "games_used": 10,
      "avg_minutes": 24.5,
      "low_minutes": false,
      "direction": "over",
      "raw_edge": 2.33,
      "edge_pct": 20.8,
      "prob_edge": 11.8,
      "model_prob": 64.9,
      "implied_prob": 53.1,
      "price": -113.0,
      "b2b": false,
      "over_price": -113.0,
      "under_price": -116.0
    },
    {
      "player": "Ja'Kobe Walter",
      "stat": "points",
      "matchup": "Miami Heat @ Toronto Raptors",
      "line": 8.5,
      "base_proj": 10.18,
      "ha_adj": -0.26,
      "def_adj": -0.02,
      "b2b_adj": 0.0,
      "bias_adj": 0.4,
      "projection": 10.3,
      "std_dev": 5.54,
      "ci_low": 4.8,
      "ci_high": 15.8,
      "season_avg": 7.36,
      "rolling_avg": 10.64,
      "games_used": 10,
      "avg_minutes": 28.1,
      "low_minutes": false,
      "direction": "over",
      "raw_edge": 1.8,
      "edge_pct": 21.2,
      "prob_edge": 12.0,
      "model_prob": 62.7,
      "implied_prob": 50.7,
      "price": -103.0,
      "b2b": false,
      "over_price": -103.0,
      "under_price": -126.5
    },
    {
      "player": "Jakob Poeltl",
      "stat": "rebounds",
      "matchup": "Miami Heat @ Toronto Raptors",
      "line": 7.5,
      "base_proj": 5.87,
      "ha_adj": 0.69,
      "def_adj": -0.0,
      "b2b_adj": 0.0,
      "bias_adj": 0.0,
      "projection": 6.56,
      "std_dev": 3.3,
      "ci_low": 3.3,
      "ci_high": 9.9,
      "season_avg": 7.28,
      "rolling_avg": 5.65,
      "games_used": 10,
      "avg_minutes": 24.5,
      "low_minutes": false,
      "direction": "under",
      "raw_edge": -0.94,
      "edge_pct": -12.5,
      "prob_edge": 7.8,
      "model_prob": 61.2,
      "implied_prob": 53.4,
      "price": -114.7,
      "b2b": false,
      "over_price": -115.0,
      "under_price": -114.7
    },
    {
      "player": "Brandon Ingram",
      "stat": "rebounds",
      "matchup": "Miami Heat @ Toronto Raptors",
      "line": 5.5,
      "base_proj": 4.69,
      "ha_adj": 0.49,
      "def_adj": -0.0,
      "b2b_adj": 0.0,
      "bias_adj": 0.0,
      "projection": 5.18,
      "std_dev": 2.01,
      "ci_low": 3.2,
      "ci_high": 7.2,
      "season_avg": 5.54,
      "rolling_avg": 4.56,
      "games_used": 10,
      "avg_minutes": 31.2,
      "low_minutes": false,
      "direction": "under",
      "raw_edge": -0.32,
      "edge_pct": -5.8,
      "prob_edge": 1.4,
      "model_prob": 56.3,
      "implied_prob": 55.0,
      "price": -122.0,
      "b2b": false,
      "over_price": -107.3,
      "under_price": -122.0
    },
    {
      "player": "Davion Mitchell",
      "stat": "rebounds",
      "matchup": "Miami Heat @ Toronto Raptors",
      "line": 2.5,
      "base_proj": 2.63,
      "ha_adj": -0.09,
      "def_adj": -0.0,
      "b2b_adj": 0.0,
      "bias_adj": 0.0,
      "projection": 2.53,
      "std_dev": 1.11,
      "ci_low": 1.4,
      "ci_high": 3.6,
      "season_avg": 2.68,
      "rolling_avg": 2.62,
      "games_used": 10,
      "avg_minutes": 29.8,
      "low_minutes": false,
      "direction": "over",
      "raw_edge": 0.03,
      "edge_pct": 1.2,
      "prob_edge": -3.1,
      "model_prob": 51.1,
      "implied_prob": 54.1,
      "price": -118.0,
      "b2b": false,
      "over_price": -118.0,
      "under_price": -112.7
    },
    {
      "player": "Mikal Bridges",
      "stat": "assists",
      "matchup": "Boston Celtics @ New York Knicks",
      "line": 3.5,
      "base_proj": 2.07,
      "ha_adj": -0.1,
      "def_adj": -0.0,
      "b2b_adj": 0.0,
      "bias_adj": 0.0,
      "projection": 1.97,
      "std_dev": 2.24,
      "ci_low": 0,
      "ci_high": 4.2,
      "season_avg": 3.73,
      "rolling_avg": 1.8,
      "games_used": 10,
      "avg_minutes": 32.1,
      "low_minutes": false,
      "direction": "under",
      "raw_edge": -1.53,
      "edge_pct": -43.7,
      "prob_edge": 14.4,
      "model_prob": 75.3,
      "implied_prob": 60.9,
      "price": -155.5,
      "b2b": false,
      "over_price": 116.5,
      "under_price": -155.5
    },
    {
      "player": "Karl-Anthony Towns",
      "stat": "assists",
      "matchup": "Boston Celtics @ New York Knicks",
      "line": 2.5,
      "base_proj": 3.8,
      "ha_adj": 0.02,
      "def_adj": -0.0,
      "b2b_adj": 0.0,
      "bias_adj": 0.0,
      "projection": 3.82,
      "std_dev": 2.9,
      "ci_low": 0.9,
      "ci_high": 6.7,
      "season_avg": 2.97,
      "rolling_avg": 3.93,
      "games_used": 10,
      "avg_minutes": 29.6,
      "low_minutes": false,
      "direction": "over",
      "raw_edge": 1.32,
      "edge_pct": 52.8,
      "prob_edge": 16.1,
      "model_prob": 67.6,
      "implied_prob": 51.5,
      "price": -106.0,
      "b2b": false,
      "over_price": -106.0,
      "under_price": -124.0
    },
    {
      "player": "Jalen Brunson",
      "stat": "points",
      "matchup": "Boston Celtics @ New York Knicks",
      "line": 25.5,
      "base_proj": 24.59,
      "ha_adj": -0.77,
      "def_adj": -0.08,
      "b2b_adj": 0.0,
      "bias_adj": 0.4,
      "projection": 24.15,
      "std_dev": 6.82,
      "ci_low": 17.3,
      "ci_high": 31.0,
      "season_avg": 26.01,
      "rolling_avg": 24.36,
      "games_used": 10,
      "avg_minutes": 36.2,
      "low_minutes": false,
      "direction": "under",
      "raw_edge": -1.35,
      "edge_pct": -5.3,
      "prob_edge": 4.4,
      "model_prob": 57.8,
      "implied_prob": 53.5,
      "price": -115.0,
      "b2b": false,
      "over_price": -113.0,
      "under_price": -115.0
    },
    {
      "player": "Mikal Bridges",
      "stat": "points",
      "matchup": "Boston Celtics @ New York Knicks",
      "line": 12.5,
      "base_proj": 14.0,
      "ha_adj": 0.82,
      "def_adj": -0.04,
      "b2b_adj": 0.0,
      "bias_adj": 0.4,
      "projection": 15.18,
      "std_dev": 4.39,
      "ci_low": 10.8,
      "ci_high": 19.6,
      "season_avg": 14.66,
      "rolling_avg": 13.89,
      "games_used": 10,
      "avg_minutes": 32.1,
      "low_minutes": false,
      "direction": "over",
      "raw_edge": 2.68,
      "edge_pct": 21.4,
      "prob_edge": 21.1,
      "model_prob": 72.9,
      "implied_prob": 51.8,
      "price": -107.5,
      "b2b": false,
      "over_price": -107.5,
      "under_price": -120.5
    },
    {
      "player": "Mikal Bridges",
      "stat": "rebounds",
      "matchup": "Boston Celtics @ New York Knicks",
      "line": 3.5,
      "base_proj": 2.78,
      "ha_adj": 0.08,
      "def_adj": -0.0,
      "b2b_adj": 0.0,
      "bias_adj": 0.0,
      "projection": 2.85,
      "std_dev": 2.11,
      "ci_low": 0.7,
      "ci_high": 5.0,
      "season_avg": 3.91,
      "rolling_avg": 2.6,
      "games_used": 10,
      "avg_minutes": 32.1,
      "low_minutes": false,
      "direction": "under",
      "raw_edge": -0.65,
      "edge_pct": -18.6,
      "prob_edge": 3.0,
      "model_prob": 62.1,
      "implied_prob": 59.1,
      "price": -144.5,
      "b2b": false,
      "over_price": 107.5,
      "under_price": -144.5
    },
    {
      "player": "Josh Hart",
      "stat": "points",
      "matchup": "Boston Celtics @ New York Knicks",
      "line": 10.5,
      "base_proj": 10.97,
      "ha_adj": -0.41,
      "def_adj": -0.03,
      "b2b_adj": 0.0,
      "bias_adj": 0.4,
      "projection": 10.93,
      "std_dev": 8.27,
      "ci_low": 2.7,
      "ci_high": 19.2,
      "season_avg": 11.92,
      "rolling_avg": 10.82,
      "games_used": 10,
      "avg_minutes": 30.5,
      "low_minutes": false,
      "direction": "over",
      "raw_edge": 0.43,
      "edge_pct": 4.1,
      "prob_edge": -1.4,
      "model_prob": 52.1,
      "implied_prob": 53.5,
      "price": -115.0,
      "b2b": false,
      "over_price": -115.0,
      "under_price": -115.0
    },
    {
      "player": "Tyrese Maxey",
      "stat": "assists",
      "matchup": "Philadelphia 76ers @ Houston Rockets",
      "line": 7.5,
      "base_proj": 6.4,
      "ha_adj": 0.03,
      "def_adj": -0.01,
      "b2b_adj": 0.0,
      "bias_adj": 0.0,
      "projection": 6.42,
      "std_dev": 2.68,
      "ci_low": 3.7,
      "ci_high": 9.1,
      "season_avg": 6.72,
      "rolling_avg": 6.34,
      "games_used": 10,
      "avg_minutes": 37.2,
      "low_minutes": false,
      "direction": "under",
      "raw_edge": -1.08,
      "edge_pct": -14.4,
      "prob_edge": 5.6,
      "model_prob": 65.7,
      "implied_prob": 60.0,
      "price": -150.3,
      "b2b": false,
      "over_price": 112.7,
      "under_price": -150.3
    },
    {
      "player": "Kevin Durant",
      "stat": "assists",
      "matchup": "Philadelphia 76ers @ Houston Rockets",
      "line": 5.5,
      "base_proj": 6.32,
      "ha_adj": -0.11,
      "def_adj": -0.01,
      "b2b_adj": 0.0,
      "bias_adj": 0.0,
      "projection": 6.21,
      "std_dev": 2.29,
      "ci_low": 3.9,
      "ci_high": 8.5,
      "season_avg": 4.74,
      "rolling_avg": 6.58,
      "games_used": 10,
      "avg_minutes": 35.7,
      "low_minutes": false,
      "direction": "over",
      "raw_edge": 0.71,
      "edge_pct": 12.9,
      "prob_edge": 10.4,
      "model_prob": 62.2,
      "implied_prob": 51.8,
      "price": -107.3,
      "b2b": false,
      "over_price": -107.3,
      "under_price": -123.0
    },
    {
      "player": "Amen Thompson",
      "stat": "assists",
      "matchup": "Philadelphia 76ers @ Houston Rockets",
      "line": 5.5,
      "base_proj": 5.84,
      "ha_adj": 0.12,
      "def_adj": -0.01,
      "b2b_adj": 0.0,
      "bias_adj": 0.0,
      "projection": 5.95,
      "std_dev": 2.58,
      "ci_low": 3.4,
      "ci_high": 8.5,
      "season_avg": 5.31,
      "rolling_avg": 5.92,
      "games_used": 10,
      "avg_minutes": 37.8,
      "low_minutes": false,
      "direction": "over",
      "raw_edge": 0.45,
      "edge_pct": 8.2,
      "prob_edge": 8.5,
      "model_prob": 56.9,
      "implied_prob": 48.4,
      "price": 106.7,
      "b2b": false,
      "over_price": 106.7,
      "under_price": -142.3
    },
    {
      "player": "Reed Sheppard",
      "stat": "assists",
      "matchup": "Philadelphia 76ers @ Houston Rockets",
      "line": 3.5,
      "base_proj": 4.08,
      "ha_adj": 0.04,
      "def_adj": -0.0,
      "b2b_adj": 0.0,
      "bias_adj": 0.0,
      "projection": 4.11,
      "std_dev": 3.66,
      "ci_low": 0.5,
      "ci_high": 7.8,
      "season_avg": 3.42,
      "rolling_avg": 4.18,
      "games_used": 10,
      "avg_minutes": 28.1,
      "low_minutes": false,
      "direction": "over",
      "raw_edge": 0.61,
      "edge_pct": 17.4,
      "prob_edge": 3.3,
      "model_prob": 56.6,
      "implied_prob": 53.3,
      "price": -114.3,
      "b2b": false,
      "over_price": -114.3,
      "under_price": -115.7
    },
    {
      "player": "Joel Embiid",
      "stat": "points",
      "matchup": "Philadelphia 76ers @ Houston Rockets",
      "line": 27.8,
      "base_proj": 28.33,
      "ha_adj": -0.67,
      "def_adj": -0.09,
      "b2b_adj": 0.0,
      "bias_adj": 0.4,
      "projection": 27.96,
      "std_dev": 5.1,
      "ci_low": 22.9,
      "ci_high": 33.1,
      "season_avg": 26.87,
      "rolling_avg": 28.56,
      "games_used": 10,
      "avg_minutes": 33.7,
      "low_minutes": false,
      "direction": "over",
      "raw_edge": 0.16,
      "edge_pct": 0.6,
      "prob_edge": 1.3,
      "model_prob": 51.3,
      "implied_prob": 50.0,
      "price": null,
      "b2b": false,
      "over_price": null,
      "under_price": -115.0
    },
    {
      "player": "Kevin Durant",
      "stat": "points",
      "matchup": "Philadelphia 76ers @ Houston Rockets",
      "line": 25.5,
      "base_proj": 26.15,
      "ha_adj": 1.33,
      "def_adj": -0.09,
      "b2b_adj": 0.0,
      "bias_adj": 0.4,
      "projection": 27.79,
      "std_dev": 5.69,
      "ci_low": 22.1,
      "ci_high": 33.5,
      "season_avg": 25.84,
      "rolling_avg": 26.2,
      "games_used": 10,
      "avg_minutes": 35.7,
      "low_minutes": false,
      "direction": "over",
      "raw_edge": 2.29,
      "edge_pct": 9.0,
      "prob_edge": 13.0,
      "model_prob": 65.6,
      "implied_prob": 52.7,
      "price": -111.3,
      "b2b": false,
      "over_price": -111.3,
      "under_price": -117.3
    },
    {
      "player": "Tyrese Maxey",
      "stat": "points",
      "matchup": "Philadelphia 76ers @ Houston Rockets",
      "line": 24.5,
      "base_proj": 24.24,
      "ha_adj": 0.71,
      "def_adj": -0.08,
      "b2b_adj": 0.0,
      "bias_adj": 0.4,
      "projection": 25.27,
      "std_dev": 4.98,
      "ci_low": 20.3,
      "ci_high": 30.3,
      "season_avg": 28.4,
      "rolling_avg": 23.56,
      "games_used": 10,
      "avg_minutes": 37.2,
      "low_minutes": false,
      "direction": "over",
      "raw_edge": 0.77,
      "edge_pct": 3.1,
      "prob_edge": 3.8,
      "model_prob": 56.1,
      "implied_prob": 52.3,
      "price": -109.7,
      "b2b": false,
      "over_price": -109.7,
      "under_price": -119.3
    },
    {
      "player": "Alperen Sengun",
      "stat": "points",
      "matchup": "Philadelphia 76ers @ Houston Rockets",
      "line": 18.5,
      "base_proj": 21.36,
      "ha_adj": 0.29,
      "def_adj": -0.07,
      "b2b_adj": 0.0,
      "bias_adj": 0.4,
      "projection": 21.98,
      "std_dev": 8.09,
      "ci_low": 13.9,
      "ci_high": 30.1,
      "season_avg": 20.51,
      "rolling_avg": 21.5,
      "games_used": 10,
      "avg_minutes": 32.2,
      "low_minutes": false,
      "direction": "over",
      "raw_edge": 3.48,
      "edge_pct": 18.8,
      "prob_edge": 14.1,
      "model_prob": 66.6,
      "implied_prob": 52.5,
      "price": -110.7,
      "b2b": false,
      "over_price": -110.7,
      "under_price": -118.0
    },
    {
      "player": "Amen Thompson",
      "stat": "points",
      "matchup": "Philadelphia 76ers @ Houston Rockets",
      "line": 17.5,
      "base_proj": 18.6,
      "ha_adj": -0.26,
      "def_adj": -0.06,
      "b2b_adj": 0.0,
      "bias_adj": 0.4,
      "projection": 18.68,
      "std_dev": 3.85,
      "ci_low": 14.8,
      "ci_high": 22.5,
      "season_avg": 17.96,
      "rolling_avg": 18.71,
      "games_used": 10,
      "avg_minutes": 37.8,
      "low_minutes": false,
      "direction": "over",
      "raw_edge": 1.18,
      "edge_pct": 6.7,
      "prob_edge": 8.3,
      "model_prob": 62.0,
      "implied_prob": 53.8,
      "price": -116.3,
      "b2b": false,
      "over_price": -116.3,
      "under_price": -112.3
    },
    {
      "player": "Paul George",
      "stat": "points",
      "matchup": "Philadelphia 76ers @ Houston Rockets",
      "line": 16.2,
      "base_proj": 22.04,
      "ha_adj": 0.93,
      "def_adj": -0.07,
      "b2b_adj": 0.0,
      "bias_adj": 0.4,
      "projection": 23.3,
      "std_dev": 8.39,
      "ci_low": 14.9,
      "ci_high": 31.7,
      "season_avg": 17.71,
      "rolling_avg": 22.75,
      "games_used": 10,
      "avg_minutes": 33.6,
      "low_minutes": false,
      "direction": "over",
      "raw_edge": 7.1,
      "edge_pct": 43.8,
      "prob_edge": 26.7,
      "model_prob": 80.1,
      "implied_prob": 53.4,
      "price": -114.7,
      "b2b": false,
      "over_price": -114.7,
      "under_price": -116.0
    },
    {
      "player": "VJ Edgecombe",
      "stat": "points",
      "matchup": "Philadelphia 76ers @ Houston Rockets",
      "line": 13.5,
      "base_proj": 18.43,
      "ha_adj": 0.64,
      "def_adj": -0.06,
      "b2b_adj": 0.0,
      "bias_adj": 0.4,
      "projection": 19.42,
      "std_dev": 9.17,
      "ci_low": 10.3,
      "ci_high": 28.6,
      "season_avg": 16.03,
      "rolling_avg": 18.82,
      "games_used": 10,
      "avg_minutes": 35.4,
      "low_minutes": false,
      "direction": "over",
      "raw_edge": 5.92,
      "edge_pct": 43.9,
      "prob_edge": 20.6,
      "model_prob": 74.1,
      "implied_prob": 53.5,
      "price": -115.0,
      "b2b": false,
      "over_price": -115.0,
      "under_price": -114.0
    },
    {
      "player": "Reed Sheppard",
      "stat": "points",
      "matchup": "Philadelphia 76ers @ Houston Rockets",
      "line": 12.5,
      "base_proj": 14.46,
      "ha_adj": -0.38,
      "def_adj": -0.05,
      "b2b_adj": 0.0,
      "bias_adj": 0.4,
      "projection": 14.43,
      "std_dev": 6.14,
      "ci_low": 8.3,
      "ci_high": 20.6,
      "season_avg": 13.58,
      "rolling_avg": 14.61,
      "games_used": 10,
      "avg_minutes": 28.1,
      "low_minutes": false,
      "direction": "over",
      "raw_edge": 1.93,
      "edge_pct": 15.4,
      "prob_edge": 9.6,
      "model_prob": 62.3,
      "implied_prob": 52.8,
      "price": -111.7,
      "b2b": false,
      "over_price": -111.7,
      "under_price": -117.7
    },
    {
      "player": "Tari Eason",
      "stat": "points",
      "matchup": "Philadelphia 76ers @ Houston Rockets",
      "line": 9.5,
      "base_proj": 10.02,
      "ha_adj": -0.03,
      "def_adj": -0.03,
      "b2b_adj": 0.0,
      "bias_adj": 0.4,
      "projection": 10.35,
      "std_dev": 5.76,
      "ci_low": 4.6,
      "ci_high": 16.1,
      "season_avg": 10.39,
      "rolling_avg": 9.96,
      "games_used": 10,
      "avg_minutes": 24.0,
      "low_minutes": false,
      "direction": "over",
      "raw_edge": 0.85,
      "edge_pct": 8.9,
      "prob_edge": 2.3,
      "model_prob": 55.9,
      "implied_prob": 53.6,
      "price": -115.5,
      "b2b": false,
      "over_price": -115.5,
      "under_price": -112.5
    },
    {
      "player": "Quentin Grimes",
      "stat": "points",
      "matchup": "Philadelphia 76ers @ Houston Rockets",
      "line": 8.5,
      "base_proj": 10.89,
      "ha_adj": 0.05,
      "def_adj": -0.04,
      "b2b_adj": 0.0,
      "bias_adj": 0.4,
      "projection": 11.31,
      "std_dev": 7.8,
      "ci_low": 3.5,
      "ci_high": 19.1,
      "season_avg": 13.36,
      "rolling_avg": 10.49,
      "games_used": 10,
      "avg_minutes": 26.1,
      "low_minutes": false,
      "direction": "over",
      "raw_edge": 2.81,
      "edge_pct": 33.1,
      "prob_edge": 12.7,
      "model_prob": 64.1,
      "implied_prob": 51.3,
      "price": -105.5,
      "b2b": false,
      "over_price": -105.5,
      "under_price": -123.5
    },
    {
      "player": "Kevin Durant",
      "stat": "rebounds",
      "matchup": "Philadelphia 76ers @ Houston Rockets",
      "line": 5.5,
      "base_proj": 5.25,
      "ha_adj": 0.04,
      "def_adj": -0.01,
      "b2b_adj": 0.0,
      "bias_adj": 0.0,
      "projection": 5.29,
      "std_dev": 1.58,
      "ci_low": 3.7,
      "ci_high": 6.9,
      "season_avg": 5.42,
      "rolling_avg": 5.22,
      "games_used": 10,
      "avg_minutes": 35.7,
      "low_minutes": false,
      "direction": "under",
      "raw_edge": -0.21,
      "edge_pct": -3.8,
      "prob_edge": 2.0,
      "model_prob": 55.3,
      "implied_prob": 53.3,
      "price": -114.0,
      "b2b": false,
      "over_price": -115.3,
      "under_price": -114.0
    },
    {
      "player": "Marcus Smart",
      "stat": "assists",
      "matchup": "Los Angeles Lakers @ Golden State Warriors",
      "line": 3.5,
      "base_proj": 2.71,
      "ha_adj": -0.18,
      "def_adj": -0.0,
      "b2b_adj": 0.0,
      "bias_adj": 0.0,
      "projection": 2.53,
      "std_dev": 1.81,
      "ci_low": 0.7,
      "ci_high": 4.3,
      "season_avg": 2.8,
      "rolling_avg": 2.69,
      "games_used": 10,
      "avg_minutes": 31.6,
      "low_minutes": false,
      "direction": "under",
      "raw_edge": -0.97,
      "edge_pct": -27.7,
      "prob_edge": 9.2,
      "model_prob": 70.4,
      "implied_prob": 61.2,
      "price": -157.7,
      "b2b": false,
      "over_price": 117.3,
      "under_price": -157.7
    },
    {
      "player": "LeBron James",
      "stat": "points",
      "matchup": "Los Angeles Lakers @ Golden State Warriors",
      "line": 24.8,
      "base_proj": 19.17,
      "ha_adj": 0.21,
      "def_adj": -0.02,
      "b2b_adj": 0.0,
      "bias_adj": 0.4,
      "projection": 19.76,
      "std_dev": 6.68,
      "ci_low": 13.1,
      "ci_high": 26.4,
      "season_avg": 20.77,
      "rolling_avg": 18.9,
      "games_used": 10,
      "avg_minutes": 34.1,
      "low_minutes": false,
      "direction": "under",
      "raw_edge": -5.04,
      "edge_pct": -20.3,
      "prob_edge": 23.9,
      "model_prob": 77.5,
      "implied_prob": 53.6,
      "price": -115.3,
      "b2b": false,
      "over_price": -113.3,
      "under_price": -115.3
    },
    {
      "player": "Rui Hachimura",
      "stat": "points",
      "matchup": "Los Angeles Lakers @ Golden State Warriors",
      "line": 14.5,
      "base_proj": 11.06,
      "ha_adj": -0.59,
      "def_adj": 0.02,
      "b2b_adj": 0.0,
      "bias_adj": 0.4,
      "projection": 10.89,
      "std_dev": 5.58,
      "ci_low": 5.3,
      "ci_high": 16.5,
      "season_avg": 11.28,
      "rolling_avg": 11.03,
      "games_used": 10,
      "avg_minutes": 24.0,
      "low_minutes": false,
      "direction": "under",
      "raw_edge": -3.61,
      "edge_pct": -24.9,
      "prob_edge": 21.5,
      "model_prob": 74.1,
      "implied_prob": 52.6,
      "price": -111.0,
      "b2b": false,
      "over_price": -117.7,
      "under_price": -111.0
    },
    {
      "player": "Luke Kennard",
      "stat": "points",
      "matchup": "Los Angeles Lakers @ Golden State Warriors",
      "line": 12.8,
      "base_proj": 8.93,
      "ha_adj": -0.62,
      "def_adj": 0.02,
      "b2b_adj": 0.0,
      "bias_adj": 0.4,
      "projection": 8.73,
      "std_dev": 5.57,
      "ci_low": 3.2,
      "ci_high": 14.3,
      "season_avg": 8.21,
      "rolling_avg": 9.05,
      "games_used": 10,
      "avg_minutes": 26.3,
      "low_minutes": false,
      "direction": "under",
      "raw_edge": -4.07,
      "edge_pct": -31.8,
      "prob_edge": 24.2,
      "model_prob": 76.8,
      "implied_prob": 52.5,
      "price": -110.7,
      "b2b": false,
      "over_price": -118.7,
      "under_price": -110.7
    },
    {
      "player": "Jake LaRavia",
      "stat": "points",
      "matchup": "Los Angeles Lakers @ Golden State Warriors",
      "line": 11.5,
      "base_proj": 6.56,
      "ha_adj": -0.12,
      "def_adj": 0.01,
      "b2b_adj": 0.0,
      "bias_adj": 0.4,
      "projection": 6.85,
      "std_dev": 4.71,
      "ci_low": 2.1,
      "ci_high": 11.6,
      "season_avg": 8.28,
      "rolling_avg": 6.28,
      "games_used": 10,
      "avg_minutes": 27.2,
      "low_minutes": false,
      "direction": "under",
      "raw_edge": -4.65,
      "edge_pct": -40.4,
      "prob_edge": 30.7,
      "model_prob": 83.8,
      "implied_prob": 53.1,
      "price": -113.3,
      "b2b": false,
      "over_price": -115.3,
      "under_price": -113.3
    },
    {
      "player": "Deandre Ayton",
      "stat": "points",
      "matchup": "Los Angeles Lakers @ Golden State Warriors",
      "line": 11.5,
      "base_proj": 10.6,
      "ha_adj": 0.52,
      "def_adj": 0.02,
      "b2b_adj": 0.0,
      "bias_adj": 0.4,
      "projection": 11.54,
      "std_dev": 4.34,
      "ci_low": 7.2,
      "ci_high": 15.9,
      "season_avg": 12.23,
      "rolling_avg": 10.34,
      "games_used": 10,
      "avg_minutes": 24.2,
      "low_minutes": false,
      "direction": "over",
      "raw_edge": 0.04,
      "edge_pct": 0.3,
      "prob_edge": -2.3,
      "model_prob": 50.4,
      "implied_prob": 52.7,
      "price": -111.3,
      "b2b": false,
      "over_price": -111.3,
      "under_price": -117.3
    },
    {
      "player": "Marcus Smart",
      "stat": "points",
      "matchup": "Los Angeles Lakers @ Golden State Warriors",
      "line": 10.5,
      "base_proj": 9.22,
      "ha_adj": -0.04,
      "def_adj": -0.01,
      "b2b_adj": 0.0,
      "bias_adj": 0.4,
      "projection": 9.57,
      "std_dev": 4.98,
      "ci_low": 4.6,
      "ci_high": 14.6,
      "season_avg": 9.47,
      "rolling_avg": 9.18,
      "games_used": 10,
      "avg_minutes": 31.6,
      "low_minutes": false,
      "direction": "under",
      "raw_edge": -0.93,
      "edge_pct": -8.9,
      "prob_edge": 3.9,
      "model_prob": 57.4,
      "implied_prob": 53.5,
      "price": -115.0,
      "b2b": false,
      "over_price": -113.0,
      "under_price": -115.0
    },
    {
      "player": "Deandre Ayton",
      "stat": "rebounds",
      "matchup": "Los Angeles Lakers @ Golden State Warriors",
      "line": 8.5,
      "base_proj": 5.99,
      "ha_adj": 0.2,
      "def_adj": 0.0,
      "b2b_adj": 0.0,
      "bias_adj": 0.0,
      "projection": 6.2,
      "std_dev": 3.3,
      "ci_low": 2.9,
      "ci_high": 9.5,
      "season_avg": 8.04,
      "rolling_avg": 5.66,
      "games_used": 10,
      "avg_minutes": 24.2,
      "low_minutes": false,
      "direction": "under",
      "raw_edge": -2.3,
      "edge_pct": -27.1,
      "prob_edge": 16.2,
      "model_prob": 75.7,
      "implied_prob": 59.5,
      "price": -146.7,
      "b2b": false,
      "over_price": 109.3,
      "under_price": -146.7
    },
    {
      "player": "Marcus Smart",
      "stat": "rebounds",
      "matchup": "Los Angeles Lakers @ Golden State Warriors",
      "line": 2.5,
      "base_proj": 2.1,
      "ha_adj": -0.11,
      "def_adj": -0.0,
      "b2b_adj": 0.0,
      "bias_adj": 0.0,
      "projection": 1.98,
      "std_dev": 1.04,
      "ci_low": 0.9,
      "ci_high": 3.0,
      "season_avg": 2.75,
      "rolling_avg": 1.99,
      "games_used": 10,
      "avg_minutes": 31.6,
      "low_minutes": false,
      "direction": "under",
      "raw_edge": -0.52,
      "edge_pct": -20.8,
      "prob_edge": 16.9,
      "model_prob": 69.1,
      "implied_prob": 52.2,
      "price": -109.3,
      "b2b": false,
      "over_price": -120.0,
      "under_price": -109.3
    },
    {
      "player": "Gui Santos",
      "stat": "assists",
      "matchup": "Los Angeles Lakers @ Golden State Warriors",
      "line": 2.5,
      "base_proj": 3.09,
      "ha_adj": -0.19,
      "def_adj": 0.0,
      "b2b_adj": 0.0,
      "bias_adj": 0.0,
      "projection": 2.9,
      "std_dev": 1.96,
      "ci_low": 0.9,
      "ci_high": 4.9,
      "season_avg": 2.29,
      "rolling_avg": 3.23,
      "games_used": 10,
      "avg_minutes": 31.4,
      "low_minutes": false,
      "direction": "over",
      "raw_edge": 0.4,
      "edge_pct": 16.0,
      "prob_edge": 8.1,
      "model_prob": 58.1,
      "implied_prob": 50.0,
      "price": 100.0,
      "b2b": false,
      "over_price": 100.0,
      "under_price": -135.0
    },
    {
      "player": "Draymond Green",
      "stat": "assists",
      "matchup": "Los Angeles Lakers @ Golden State Warriors",
      "line": 6.5,
      "base_proj": 6.8,
      "ha_adj": -0.23,
      "def_adj": 0.0,
      "b2b_adj": 0.0,
      "bias_adj": 0.0,
      "projection": 6.57,
      "std_dev": 3.17,
      "ci_low": 3.4,
      "ci_high": 9.7,
      "season_avg": 5.52,
      "rolling_avg": 7.0,
      "games_used": 10,
      "avg_minutes": 30.1,
      "low_minutes": false,
      "direction": "over",
      "raw_edge": 0.07,
      "edge_pct": 1.1,
      "prob_edge": -2.6,
      "model_prob": 50.9,
      "implied_prob": 53.5,
      "price": -115.0,
      "b2b": false,
      "over_price": -115.0,
      "under_price": -115.0
    },
    {
      "player": "Stephen Curry",
      "stat": "points",
      "matchup": "Los Angeles Lakers @ Golden State Warriors",
      "line": 23.5,
      "base_proj": 24.25,
      "ha_adj": -1.78,
      "def_adj": 0.04,
      "b2b_adj": 0.0,
      "bias_adj": 0.4,
      "projection": 22.91,
      "std_dev": 6.93,
      "ci_low": 16.0,
      "ci_high": 29.8,
      "season_avg": 27.0,
      "rolling_avg": 23.8,
      "games_used": 10,
      "avg_minutes": 27.6,
      "low_minutes": false,
      "direction": "under",
      "raw_edge": -0.59,
      "edge_pct": -2.5,
      "prob_edge": 1.0,
      "model_prob": 53.4,
      "implied_prob": 52.4,
      "price": -110.0,
      "b2b": false,
      "over_price": -120.0,
      "under_price": -110.0
    },
    {
      "player": "Brandin Podziemski",
      "stat": "points",
      "matchup": "Los Angeles Lakers @ Golden State Warriors",
      "line": 15.5,
      "base_proj": 18.3,
      "ha_adj": 0.61,
      "def_adj": 0.03,
      "b2b_adj": 0.0,
      "bias_adj": 0.4,
      "projection": 19.34,
      "std_dev": 5.54,
      "ci_low": 13.8,
      "ci_high": 24.9,
      "season_avg": 13.62,
      "rolling_avg": 19.06,
      "games_used": 10,
      "avg_minutes": 31.4,
      "low_minutes": false,
      "direction": "over",
      "raw_edge": 3.84,
      "edge_pct": 24.8,
      "prob_edge": 24.4,
      "model_prob": 75.6,
      "implied_prob": 51.2,
      "price": -105.0,
      "b2b": false,
      "over_price": -105.0,
      "under_price": -125.0
    },
    {
      "player": "Draymond Green",
      "stat": "points",
      "matchup": "Los Angeles Lakers @ Golden State Warriors",
      "line": 9.5,
      "base_proj": 7.86,
      "ha_adj": -0.02,
      "def_adj": 0.01,
      "b2b_adj": 0.0,
      "bias_adj": 0.4,
      "projection": 8.25,
      "std_dev": 4.63,
      "ci_low": 3.6,
      "ci_high": 12.9,
      "season_avg": 8.5,
      "rolling_avg": 7.76,
      "games_used": 10,
      "avg_minutes": 30.1,
      "low_minutes": false,
      "direction": "under",
      "raw_edge": -1.25,
      "edge_pct": -13.2,
      "prob_edge": 4.1,
      "model_prob": 60.6,
      "implied_prob": 56.5,
      "price": -130.0,
      "b2b": false,
      "over_price": -105.0,
      "under_price": -130.0
    },
    {
      "player": "Pat Spencer",
      "stat": "points",
      "matchup": "Los Angeles Lakers @ Golden State Warriors",
      "line": 9.5,
      "base_proj": 9.7,
      "ha_adj": -0.88,
      "def_adj": 0.02,
      "b2b_adj": 0.0,
      "bias_adj": 0.4,
      "projection": 9.23,
      "std_dev": 4.92,
      "ci_low": 4.3,
      "ci_high": 14.2,
      "season_avg": 7.22,
      "rolling_avg": 10.1,
      "games_used": 10,
      "avg_minutes": 24.1,
      "low_minutes": false,
      "direction": "under",
      "raw_edge": -0.27,
      "edge_pct": -2.8,
      "prob_edge": -3.4,
      "model_prob": 52.2,
      "implied_prob": 55.6,
      "price": -125.0,
      "b2b": false,
      "over_price": -105.0,
      "under_price": -125.0
    },
    {
      "player": "Draymond Green",
      "stat": "rebounds",
      "matchup": "Los Angeles Lakers @ Golden State Warriors",
      "line": 6.5,
      "base_proj": 5.49,
      "ha_adj": 0.11,
      "def_adj": 0.0,
      "b2b_adj": 0.0,
      "bias_adj": 0.0,
      "projection": 5.6,
      "std_dev": 1.8,
      "ci_low": 3.8,
      "ci_high": 7.4,
      "season_avg": 5.55,
      "rolling_avg": 5.48,
      "games_used": 10,
      "avg_minutes": 30.1,
      "low_minutes": false,
      "direction": "under",
      "raw_edge": -0.9,
      "edge_pct": -13.8,
      "prob_edge": 8.4,
      "model_prob": 69.1,
      "implied_prob": 60.8,
      "price": -155.0,
      "b2b": false,
      "over_price": 115.0,
      "under_price": -155.0
    },
    {
      "player": "Gui Santos",
      "stat": "rebounds",
      "matchup": "Los Angeles Lakers @ Golden State Warriors",
      "line": 4.5,
      "base_proj": 4.68,
      "ha_adj": -0.64,
      "def_adj": 0.0,
      "b2b_adj": 0.0,
      "bias_adj": 0.0,
      "projection": 4.04,
      "std_dev": 2.05,
      "ci_low": 2.0,
      "ci_high": 6.1,
      "season_avg": 3.88,
      "rolling_avg": 4.81,
      "games_used": 10,
      "avg_minutes": 31.4,
      "low_minutes": false,
      "direction": "under",
      "raw_edge": -0.46,
      "edge_pct": -10.2,
      "prob_edge": 5.4,
      "model_prob": 58.9,
      "implied_prob": 53.5,
      "price": -115.0,
      "b2b": false,
      "over_price": -115.0,
      "under_price": -115.0
    }
  ],
  "picks": [
    {
      "player": "Jake LaRavia",
      "stat": "points",
      "matchup": "Los Angeles Lakers @ Golden State Warriors",
      "line": 11.5,
      "base_proj": 6.56,
      "ha_adj": -0.12,
      "def_adj": 0.01,
      "b2b_adj": 0.0,
      "bias_adj": 0.4,
      "projection": 6.85,
      "std_dev": 4.71,
      "ci_low": 2.1,
      "ci_high": 11.6,
      "season_avg": 8.28,
      "rolling_avg": 6.28,
      "games_used": 10,
      "avg_minutes": 27.2,
      "low_minutes": false,
      "direction": "under",
      "raw_edge": -4.65,
      "edge_pct": -40.4,
      "prob_edge": 30.7,
      "model_prob": 83.8,
      "implied_prob": 53.1,
      "price": -113.3,
      "b2b": false,
      "over_price": -115.3,
      "under_price": -113.3,
      "outcome": "WIN",
      "result": 1.0,
      "actual": 0.0,
      "settled_at": "2026-04-10T14:41:04.745636Z",
      "sport_id": "nba_props"
    },
    {
      "player": "Brandin Podziemski",
      "stat": "points",
      "matchup": "Los Angeles Lakers @ Golden State Warriors",
      "line": 15.5,
      "base_proj": 18.3,
      "ha_adj": 0.61,
      "def_adj": 0.03,
      "b2b_adj": 0.0,
      "bias_adj": 0.4,
      "projection": 19.34,
      "std_dev": 5.54,
      "ci_low": 13.8,
      "ci_high": 24.9,
      "season_avg": 13.62,
      "rolling_avg": 19.06,
      "games_used": 10,
      "avg_minutes": 31.4,
      "low_minutes": false,
      "direction": "over",
      "raw_edge": 3.84,
      "edge_pct": 24.8,
      "prob_edge": 24.4,
      "model_prob": 75.6,
      "implied_prob": 51.2,
      "price": -105.0,
      "b2b": false,
      "over_price": -105.0,
      "under_price": -125.0,
      "outcome": "LOSS",
      "result": 0.0,
      "actual": 0.0,
      "settled_at": "2026-04-10T14:41:04.745663Z",
      "sport_id": "nba_props"
    },
    {
      "player": "Luke Kennard",
      "stat": "points",
      "matchup": "Los Angeles Lakers @ Golden State Warriors",
      "line": 12.8,
      "base_proj": 8.93,
      "ha_adj": -0.62,
      "def_adj": 0.02,
      "b2b_adj": 0.0,
      "bias_adj": 0.4,
      "projection": 8.73,
      "std_dev": 5.57,
      "ci_low": 3.2,
      "ci_high": 14.3,
      "season_avg": 8.21,
      "rolling_avg": 9.05,
      "games_used": 10,
      "avg_minutes": 26.3,
      "low_minutes": false,
      "direction": "under",
      "raw_edge": -4.07,
      "edge_pct": -31.8,
      "prob_edge": 24.2,
      "model_prob": 76.8,
      "implied_prob": 52.5,
      "price": -110.7,
      "b2b": false,
      "over_price": -118.7,
      "under_price": -110.7,
      "outcome": "WIN",
      "result": 1.0,
      "actual": 0.0,
      "settled_at": "2026-04-10T14:41:04.745677Z",
      "sport_id": "nba_props"
    },
    {
      "player": "LeBron James",
      "stat": "points",
      "matchup": "Los Angeles Lakers @ Golden State Warriors",
      "line": 24.8,
      "base_proj": 19.17,
      "ha_adj": 0.21,
      "def_adj": -0.02,
      "b2b_adj": 0.0,
      "bias_adj": 0.4,
      "projection": 19.76,
      "std_dev": 6.68,
      "ci_low": 13.1,
      "ci_high": 26.4,
      "season_avg": 20.77,
      "rolling_avg": 18.9,
      "games_used": 10,
      "avg_minutes": 34.1,
      "low_minutes": false,
      "direction": "under",
      "raw_edge": -5.04,
      "edge_pct": -20.3,
      "prob_edge": 23.9,
      "model_prob": 77.5,
      "implied_prob": 53.6,
      "price": -115.3,
      "b2b": false,
      "over_price": -113.3,
      "under_price": -115.3,
      "outcome": "WIN",
      "result": 1.0,
      "actual": 0.0,
      "settled_at": "2026-04-10T14:41:04.745687Z",
      "sport_id": "nba_props"
    },
    {
      "player": "Rui Hachimura",
      "stat": "points",
      "matchup": "Los Angeles Lakers @ Golden State Warriors",
      "line": 14.5,
      "base_proj": 11.06,
      "ha_adj": -0.59,
      "def_adj": 0.02,
      "b2b_adj": 0.0,
      "bias_adj": 0.4,
      "projection": 10.89,
      "std_dev": 5.58,
      "ci_low": 5.3,
      "ci_high": 16.5,
      "season_avg": 11.28,
      "rolling_avg": 11.03,
      "games_used": 10,
      "avg_minutes": 24.0,
      "low_minutes": false,
      "direction": "under",
      "raw_edge": -3.61,
      "edge_pct": -24.9,
      "prob_edge": 21.5,
      "model_prob": 74.1,
      "implied_prob": 52.6,
      "price": -111.0,
      "b2b": false,
      "over_price": -117.7,
      "under_price": -111.0,
      "outcome": "WIN",
      "result": 1.0,
      "actual": 0.0,
      "settled_at": "2026-04-10T14:41:04.745697Z",
      "sport_id": "nba_props"
    },
    {
      "player": "VJ Edgecombe",
      "stat": "points",
      "matchup": "Philadelphia 76ers @ Houston Rockets",
      "line": 13.5,
      "base_proj": 18.43,
      "ha_adj": 0.64,
      "def_adj": -0.06,
      "b2b_adj": 0.0,
      "bias_adj": 0.4,
      "projection": 19.42,
      "std_dev": 9.17,
      "ci_low": 10.3,
      "ci_high": 28.6,
      "season_avg": 16.03,
      "rolling_avg": 18.82,
      "games_used": 10,
      "avg_minutes": 35.4,
      "low_minutes": false,
      "direction": "over",
      "raw_edge": 5.92,
      "edge_pct": 43.9,
      "prob_edge": 20.6,
      "model_prob": 74.1,
      "implied_prob": 53.5,
      "price": -115.0,
      "b2b": false,
      "over_price": -115.0,
      "under_price": -114.0,
      "outcome": "LOSS",
      "result": 0.0,
      "actual": 0.0,
      "settled_at": "2026-04-10T14:41:04.745708Z",
      "sport_id": "nba_props"
    }
  ]
}